odoo/addons/stock_picking_partner_note/README.rst
odoo/addons/stock_picking_partner_note/__init__.py
odoo/addons/stock_picking_partner_note/__manifest__.py
odoo/addons/stock_picking_partner_note/i18n/fr.po
odoo/addons/stock_picking_partner_note/i18n/stock_picking_partner_note.pot
odoo/addons/stock_picking_partner_note/models/__init__.py
odoo/addons/stock_picking_partner_note/models/res_partner.py
odoo/addons/stock_picking_partner_note/models/stock_picking.py
odoo/addons/stock_picking_partner_note/models/stock_picking_note.py
odoo/addons/stock_picking_partner_note/models/stock_picking_note_type.py
odoo/addons/stock_picking_partner_note/models/stock_picking_type.py
odoo/addons/stock_picking_partner_note/readme/CONFIGURE.rst
odoo/addons/stock_picking_partner_note/readme/CONTRIBUTORS.rst
odoo/addons/stock_picking_partner_note/readme/DESCRIPTION.rst
odoo/addons/stock_picking_partner_note/security/ir.model.access.csv
odoo/addons/stock_picking_partner_note/static/description/icon.png
odoo/addons/stock_picking_partner_note/static/description/index.html
odoo/addons/stock_picking_partner_note/tests/__init__.py
odoo/addons/stock_picking_partner_note/tests/test_stock_picking_partner_note.py
odoo/addons/stock_picking_partner_note/views/res_partner.xml
odoo/addons/stock_picking_partner_note/views/stock_picking_note.xml
odoo/addons/stock_picking_partner_note/views/stock_picking_note_type.xml
odoo/addons/stock_picking_partner_note/views/stock_picking_partner_note_menus.xml
odoo/addons/stock_picking_partner_note/views/stock_picking_type.xml
odoo14_addon_stock_picking_partner_note-14.0.1.0.2.dist-info/METADATA
odoo14_addon_stock_picking_partner_note-14.0.1.0.2.dist-info/WHEEL
odoo14_addon_stock_picking_partner_note-14.0.1.0.2.dist-info/top_level.txt
odoo14_addon_stock_picking_partner_note-14.0.1.0.2.dist-info/RECORD
